tts_webui_extension/log_viewer/__init__.py
tts_webui_extension/log_viewer/analyzer.py
tts_webui_extension/log_viewer/main.py
tts_webui_extension/log_viewer/tab_all_logs.py
tts_webui_extension/log_viewer/tab_pip_install.py
tts_webui_extension/log_viewer/tab_pip_uninstall.py
tts_webui_extension/log_viewer/utils.py
tts_webui_extension_log_viewer-0.2.0.dist-info/licenses/LICENSE
tts_webui_extension_log_viewer-0.2.0.dist-info/METADATA
tts_webui_extension_log_viewer-0.2.0.dist-info/WHEEL
tts_webui_extension_log_viewer-0.2.0.dist-info/top_level.txt
tts_webui_extension_log_viewer-0.2.0.dist-info/RECORD
