Metadata-Version: 2.4
Name: tts_webui_extension.log_viewer
Version: 0.2.0
Summary: View, search, and manage log files from the TTS Generation WebUI
Author: rsxdalv
License: MIT
Project-URL: Homepage, https://github.com/rsxdalv/tts-generation-webui
Project-URL: Repository, https://github.com/rsxdalv/tts_webui_extension.log_viewer
Project-URL: Issues, https://github.com/rsxdalv/tts_webui_extension.log_viewer/issues
Keywords: tts,gradio,log-viewer,extension
Classifier: Development Status :: 4 - Beta
Classifier: Intended Audience :: Developers
Classifier: License :: OSI Approved :: MIT License
Classifier: Programming Language :: Python :: 3
Classifier: Programming Language :: Python :: 3.8
Classifier: Programming Language :: Python :: 3.9
Classifier: Programming Language :: Python :: 3.10
Classifier: Programming Language :: Python :: 3.11
Classifier: Operating System :: OS Independent
Requires-Python: >=3.8
License-File: LICENSE
Requires-Dist: gradio>=4.0.0
Dynamic: license-file
